evok_ws_client/__init__.py
evok_ws_client/client.py
evok_ws_client-0.0.4.dist-info/LICENSE
evok_ws_client-0.0.4.dist-info/METADATA
evok_ws_client-0.0.4.dist-info/WHEEL
evok_ws_client-0.0.4.dist-info/top_level.txt
evok_ws_client-0.0.4.dist-info/RECORD
