Metadata-Version: 2.1
Name: evok-ws-client
Version: 0.0.4
Summary: Client for connectin to Unipi devices runing EVOK API via websockets
Home-page: https://github.com/marko2276/evok-ws-client
Author: Marko Vaupotic
License: MIT
Keywords: evok,unipi,websockets,home-assistant
Classifier: Development Status :: 3 - Alpha
Classifier: Intended Audience :: Developers
Classifier: Topic :: Software Development :: Build Tools
Classifier: License :: OSI Approved :: MIT License
Classifier: Programming Language :: Python :: 3
Requires-Python: >=3
License-File: LICENSE
Requires-Dist: websockets
